{
  "@context": "https://doi.org/10.5063/schema/codemeta-2.0",
  "@type": "SoftwareSourceCode",
  "identifier": "restatis",
  "description": "A RESTful API wrapper to access to the \"GENESIS\" databases of the Federal Statistical Office of Germany (Destatis): 1) <https://www-genesis.destatis.de>, 2) <https://www.regionalstatistik.de>, 3) <https://www.bildungsmonitoring.de>, 4) <https://www.statistikdaten.bayern.de>, 5) <https://www.landesdatenbank.nrw.de>, 6) <https://genesis.sachsen-anhalt.de>.",
  "name": "restatis: RESTful API Wrapper to Access Data from the Federal Statistical Office of Germany (Destatis)",
  "relatedLink": "https://long39ng.github.io/restatis",
  "codeRepository": "https://github.com/long39ng/restatis",
  "issueTracker": "https://github.com/long39ng/restatis/issues",
  "license": "https://spdx.org/licenses/MIT",
  "version": "0.1.0.9000",
  "programmingLanguage": {
    "@type": "ComputerLanguage",
    "name": "R",
    "url": "https://r-project.org"
  },
  "runtimePlatform": "R version 4.1.2 (2021-11-01)",
  "author": [
    {
      "@type": "Person",
      "givenName": "Long",
      "familyName": "Nguyen",
      "email": "long.nguyen@uni-bielefeld.de",
      "@id": "https://orcid.org/0000-0001-8878-7386"
    }
  ],
  "maintainer": [
    {
      "@type": "Person",
      "givenName": "Long",
      "familyName": "Nguyen",
      "email": "long.nguyen@uni-bielefeld.de",
      "@id": "https://orcid.org/0000-0001-8878-7386"
    }
  ],
  "softwareSuggestions": [
    {
      "@type": "SoftwareApplication",
      "identifier": "testthat",
      "name": "testthat",
      "version": ">= 3.0.0",
      "provider": {
        "@id": "https://cran.r-project.org",
        "@type": "Organization",
        "name": "Comprehensive R Archive Network (CRAN)",
        "url": "https://cran.r-project.org"
      },
      "sameAs": "https://CRAN.R-project.org/package=testthat"
    },
    {
      "@type": "SoftwareApplication",
      "identifier": "tibble",
      "name": "tibble",
      "provider": {
        "@id": "https://cran.r-project.org",
        "@type": "Organization",
        "name": "Comprehensive R Archive Network (CRAN)",
        "url": "https://cran.r-project.org"
      },
      "sameAs": "https://CRAN.R-project.org/package=tibble"
    }
  ],
  "softwareRequirements": {
    "1": {
      "@type": "SoftwareApplication",
      "identifier": "askpass",
      "name": "askpass",
      "provider": {
        "@id": "https://cran.r-project.org",
        "@type": "Organization",
        "name": "Comprehensive R Archive Network (CRAN)",
        "url": "https://cran.r-project.org"
      },
      "sameAs": "https://CRAN.R-project.org/package=askpass"
    },
    "2": {
      "@type": "SoftwareApplication",
      "identifier": "httr",
      "name": "httr",
      "provider": {
        "@id": "https://cran.r-project.org",
        "@type": "Organization",
        "name": "Comprehensive R Archive Network (CRAN)",
        "url": "https://cran.r-project.org"
      },
      "sameAs": "https://CRAN.R-project.org/package=httr"
    },
    "3": {
      "@type": "SoftwareApplication",
      "identifier": "jsonlite",
      "name": "jsonlite",
      "provider": {
        "@id": "https://cran.r-project.org",
        "@type": "Organization",
        "name": "Comprehensive R Archive Network (CRAN)",
        "url": "https://cran.r-project.org"
      },
      "sameAs": "https://CRAN.R-project.org/package=jsonlite"
    },
    "4": {
      "@type": "SoftwareApplication",
      "identifier": "keyring",
      "name": "keyring",
      "provider": {
        "@id": "https://cran.r-project.org",
        "@type": "Organization",
        "name": "Comprehensive R Archive Network (CRAN)",
        "url": "https://cran.r-project.org"
      },
      "sameAs": "https://CRAN.R-project.org/package=keyring"
    },
    "5": {
      "@type": "SoftwareApplication",
      "identifier": "memoise",
      "name": "memoise",
      "provider": {
        "@id": "https://cran.r-project.org",
        "@type": "Organization",
        "name": "Comprehensive R Archive Network (CRAN)",
        "url": "https://cran.r-project.org"
      },
      "sameAs": "https://CRAN.R-project.org/package=memoise"
    },
    "6": {
      "@type": "SoftwareApplication",
      "identifier": "readr",
      "name": "readr",
      "provider": {
        "@id": "https://cran.r-project.org",
        "@type": "Organization",
        "name": "Comprehensive R Archive Network (CRAN)",
        "url": "https://cran.r-project.org"
      },
      "sameAs": "https://CRAN.R-project.org/package=readr"
    },
    "SystemRequirements": null
  },
  "fileSize": "69.604KB",
  "readme": "https://github.com/long39ng/restatis/blob/main/README.md",
  "contIntegration": "https://github.com/long39ng/restatis/actions",
  "developmentStatus": "https://lifecycle.r-lib.org/articles/stages.html#experimental"
}
